LiyongPythonJinxingShujufenxiZhongwenDierBanSeancheney/README.md
LiyongPythonJinxingShujufenxiZhongwenDierBanSeancheney/__init__.py
LiyongPythonJinxingShujufenxiZhongwenDierBanSeancheney/__main__.py
LiyongPythonJinxingShujufenxiZhongwenDierBanSeancheney/file.epub
LiyongPythonJinxingShujufenxiZhongwenDierBanSeancheney/index.html
LiyongPythonJinxingShujufenxiZhongwenDierBanSeancheney/css/__init__.py
LiyongPythonJinxingShujufenxiZhongwenDierBanSeancheney/css/annotations.css
LiyongPythonJinxingShujufenxiZhongwenDierBanSeancheney/css/main.css
LiyongPythonJinxingShujufenxiZhongwenDierBanSeancheney/css/normalize.css
LiyongPythonJinxingShujufenxiZhongwenDierBanSeancheney/css/popup.css
LiyongPythonJinxingShujufenxiZhongwenDierBanSeancheney/font/__init__.py
LiyongPythonJinxingShujufenxiZhongwenDierBanSeancheney/font/fontello.eot
LiyongPythonJinxingShujufenxiZhongwenDierBanSeancheney/font/fontello.svg
LiyongPythonJinxingShujufenxiZhongwenDierBanSeancheney/font/fontello.ttf
LiyongPythonJinxingShujufenxiZhongwenDierBanSeancheney/font/fontello.woff
LiyongPythonJinxingShujufenxiZhongwenDierBanSeancheney/img/__init__.py
LiyongPythonJinxingShujufenxiZhongwenDierBanSeancheney/img/annotator-glyph-sprite.png
LiyongPythonJinxingShujufenxiZhongwenDierBanSeancheney/img/annotator-icon-sprite.png
LiyongPythonJinxingShujufenxiZhongwenDierBanSeancheney/img/apple-touch-icon.png
LiyongPythonJinxingShujufenxiZhongwenDierBanSeancheney/img/cancelfullscreen.png
LiyongPythonJinxingShujufenxiZhongwenDierBanSeancheney/img/close.png
LiyongPythonJinxingShujufenxiZhongwenDierBanSeancheney/img/fullscreen.png
LiyongPythonJinxingShujufenxiZhongwenDierBanSeancheney/img/loader.gif
LiyongPythonJinxingShujufenxiZhongwenDierBanSeancheney/img/menu-icon.png
LiyongPythonJinxingShujufenxiZhongwenDierBanSeancheney/img/save.png
LiyongPythonJinxingShujufenxiZhongwenDierBanSeancheney/img/saved.png
LiyongPythonJinxingShujufenxiZhongwenDierBanSeancheney/img/settings-s.png
liyong_python_jinxing_shujufenxi_zhongwen_dier_ban_seancheney-2024.3.4.0.dist-info/METADATA
liyong_python_jinxing_shujufenxi_zhongwen_dier_ban_seancheney-2024.3.4.0.dist-info/WHEEL
liyong_python_jinxing_shujufenxi_zhongwen_dier_ban_seancheney-2024.3.4.0.dist-info/entry_points.txt
liyong_python_jinxing_shujufenxi_zhongwen_dier_ban_seancheney-2024.3.4.0.dist-info/top_level.txt
liyong_python_jinxing_shujufenxi_zhongwen_dier_ban_seancheney-2024.3.4.0.dist-info/RECORD
